my_own_package/__init__.py
daniel_first_package-0.1.0.dist-info/METADATA
daniel_first_package-0.1.0.dist-info/WHEEL
daniel_first_package-0.1.0.dist-info/top_level.txt
daniel_first_package-0.1.0.dist-info/RECORD
