Metadata-Version: 2.1
Name: daniel-first-package
Version: 0.1.0
Summary: daniel first pack
Author: daniel
Author-email: vrancianudaniel@icloud.com
License: UNKNOWN
Platform: UNKNOWN
